LICENSE.txt
MANIFEST.in
README.rst
setup.cfg
setup.py
ya_ma.py
ya_ma.egg-info/PKG-INFO
ya_ma.egg-info/SOURCES.txt
ya_ma.egg-info/dependency_links.txt
ya_ma.egg-info/requires.txt
ya_ma.egg-info/top_level.txt