Metadata-Version: 2.1
Name: ya-ma
Version: 0.3.7
Summary: YANDEX transport API client library
Home-page: https://github.com/rishatik92/ya_ma
Author: Askarov Rishat Ramilovich
Author-email: rishatik92@gmail.com
License: MIT
Project-URL: Source Code, https://github.com/rishatik92/ya_ma
Project-URL: Bug Tracker, https://github.com/rishatik92/ya_ma/issues
Project-URL: Say Thanks!, https://saythanks.io/to/rishatik92
Keywords: pypi,yandex transport,packages,pip
Platform: UNKNOWN
Classifier: Development Status :: 4 - Beta
Classifier: Programming Language :: Python :: 2
Classifier: Programming Language :: Python :: 2.7
Classifier: Programming Language :: Python :: 3
Classifier: Programming Language :: Python :: 3.4
Classifier: Programming Language :: Python :: 3.5
Classifier: Programming Language :: Python :: 3.6
Classifier: Programming Language :: Python :: 3.7
Classifier: Programming Language :: Python :: 3.8
Classifier: Programming Language :: Python :: Implementation :: CPython
Classifier: Programming Language :: Python :: Implementation :: PyPy
Classifier: License :: OSI Approved :: MIT License
Classifier: Topic :: Software Development :: Libraries :: Python Modules
Classifier: Topic :: System :: Software Distribution
Classifier: Topic :: Text Processing :: Markup :: HTML
Requires-Python: >=2.7, !=3.0.*, !=3.1.*, !=3.2.*, !=3.3.*, <4
